{
  "id": "system-CorpInfo",
  "pack": "system",
  "code": "CorpInfo",
  "name": "公司信息详情",
  "description": "公司信息详情信息",
  "sortCode": "3035",
  "classification": null,
  "tags": "公司信息,详情",
  "dataModelType": "DataMap",
  "dataModel": "AUTH_CORP",
  "query": {
    "select": "select",
    "selectItems": [],
    "from": "AUTH_CORP",
    "where": "CORP_ID=:corpId",
    "groupBy": null,
    "having": null,
    "orderBy": "CREATED_TIME DESC"
  },
  "handler": null,
  "formUIHint": {
    "columnNumber": 2,
    "formStyle": "DetailInfo"
  },
  "elements": [
    {
      "dataformId": "system-CorpInfo",
      "code": "corpId",
      "primaryKey": true,
      "primaryKeyGenerator": null,
      "sortCode": "0000",
      "name": "主键ID",
      "nameI18nCode": null,
      "column": "CORP_ID",
      "table": null,
      "updateable": true,
      "sortable": false,
      "persist": true,
      "dataType": "String",
      "decimalDigits": -1,
      "defaultValue": null,
      "summaryExpression": null,
      "enabled": true,
      "group": null,
      "groupI18nCode": null,
      "subGroup": null,
      "subGroupI18nCode": null,
      "limitedLength": -1,
      "multiplier": 1,
      "elementUIHint": {
        "editStyle": "Text",
        "dataFormat": "String",
        "visible": true,
        "reading": true,
        "readonly": false,
        "required": false,
        "colspan": 1,
        "textAlign": "Left",
        "placeholder": null,
        "dictCodeMode": null,
        "dictCodeExpr": null,
        "dictCodeLazy": false,
        "dictCodeTreeLeafOnly": false,
        "dictCodeTreeFull": false,
        "prefix": null,
        "suffix": null,
        "tips": null,
        "tipsI18nCode": null,
        "note": null,
        "noteI18nCode": null,
        "rank": 0,
        "mediaQuery": "xs",
        "eventExpr": null,
        "htmlStyle": null
      },
      "validatorList": [],
      "revision": 0,
      "createdBy": null,
      "createdTime": null,
      "updatedBy": null,
      "updatedTime": null
    },
    {
      "dataformId": "system-CorpInfo",
      "code": "corpName",
      "primaryKey": false,
      "primaryKeyGenerator": null,
      "sortCode": "0010",
      "name": "主体公司名称",
      "nameI18nCode": null,
      "column": "CORP_NAME",
      "table": null,
      "updateable": true,
      "sortable": false,
      "persist": true,
      "dataType": "String",
      "decimalDigits": -1,
      "defaultValue": null,
      "summaryExpression": null,
      "enabled": true,
      "group": null,
      "groupI18nCode": null,
      "subGroup": null,
      "subGroupI18nCode": null,
      "limitedLength": -1,
      "multiplier": 1,
      "elementUIHint": {
        "editStyle": "Text",
        "dataFormat": "String",
        "visible": true,
        "reading": false,
        "readonly": false,
        "required": true,
        "colspan": 2,
        "textAlign": "Left",
        "placeholder": null,
        "dictCodeMode": null,
        "dictCodeExpr": null,
        "dictCodeLazy": false,
        "dictCodeTreeLeafOnly": false,
        "dictCodeTreeFull": false,
        "prefix": null,
        "suffix": null,
        "tips": null,
        "tipsI18nCode": null,
        "note": null,
        "noteI18nCode": null,
        "rank": 0,
        "mediaQuery": "xs",
        "eventExpr": null,
        "htmlStyle": "{\"width\":\"250px\"}"
      },
      "validatorList": [],
      "revision": 0,
      "createdBy": null,
      "createdTime": null,
      "updatedBy": null,
      "updatedTime": null
    },
    {
      "dataformId": "system-CorpInfo",
      "code": "corpShortName",
      "primaryKey": false,
      "primaryKeyGenerator": null,
      "sortCode": "0020",
      "name": "简称",
      "nameI18nCode": null,
      "column": "CORP_SHORT_NAME",
      "table": null,
      "updateable": true,
      "sortable": false,
      "persist": true,
      "dataType": "String",
      "decimalDigits": -1,
      "defaultValue": null,
      "summaryExpression": null,
      "enabled": true,
      "group": null,
      "groupI18nCode": null,
      "subGroup": null,
      "subGroupI18nCode": null,
      "limitedLength": -1,
      "multiplier": 1,
      "elementUIHint": {
        "editStyle": "Text",
        "dataFormat": "String",
        "visible": true,
        "reading": false,
        "readonly": false,
        "required": true,
        "colspan": 2,
        "textAlign": "Left",
        "placeholder": null,
        "dictCodeMode": null,
        "dictCodeExpr": null,
        "dictCodeLazy": false,
        "dictCodeTreeLeafOnly": false,
        "dictCodeTreeFull": false,
        "prefix": null,
        "suffix": null,
        "tips": null,
        "tipsI18nCode": null,
        "note": null,
        "noteI18nCode": null,
        "rank": 0,
        "mediaQuery": "xs",
        "eventExpr": null,
        "htmlStyle": "{\"width\":\"250px\"}"
      },
      "validatorList": [],
      "revision": 0,
      "createdBy": null,
      "createdTime": null,
      "updatedBy": null,
      "updatedTime": null
    },
    {
      "dataformId": "system-CorpInfo",
      "code": "creditCode",
      "primaryKey": false,
      "primaryKeyGenerator": null,
      "sortCode": "0030",
      "name": "统一社会信用代码",
      "nameI18nCode": null,
      "column": "UNIFIED_CREDIT_CODE",
      "table": null,
      "updateable": true,
      "sortable": false,
      "persist": true,
      "dataType": "String",
      "decimalDigits": -1,
      "defaultValue": null,
      "summaryExpression": null,
      "enabled": true,
      "group": null,
      "groupI18nCode": null,
      "subGroup": null,
      "subGroupI18nCode": null,
      "limitedLength": -1,
      "multiplier": 1,
      "elementUIHint": {
        "editStyle": "Text",
        "dataFormat": "String",
        "visible": true,
        "reading": false,
        "readonly": false,
        "required": true,
        "colspan": 2,
        "textAlign": "Left",
        "placeholder": null,
        "dictCodeMode": null,
        "dictCodeExpr": null,
        "dictCodeLazy": false,
        "dictCodeTreeLeafOnly": false,
        "dictCodeTreeFull": false,
        "prefix": null,
        "suffix": null,
        "tips": null,
        "tipsI18nCode": null,
        "note": null,
        "noteI18nCode": null,
        "rank": 0,
        "mediaQuery": "xs",
        "eventExpr": null,
        "htmlStyle": "{\"width\":\"250px\"}"
      },
      "validatorList": [],
      "revision": 0,
      "createdBy": null,
      "createdTime": null,
      "updatedBy": null,
      "updatedTime": null
    },
    {
      "dataformId": "system-CorpInfo",
      "code": "taxNature",
      "primaryKey": false,
      "primaryKeyGenerator": null,
      "sortCode": "0040",
      "name": "主体公司纳税性质",
      "nameI18nCode": null,
      "column": "TAX_NATURE",
      "table": null,
      "updateable": true,
      "sortable": false,
      "persist": true,
      "dataType": "String",
      "decimalDigits": -1,
      "defaultValue": null,
      "summaryExpression": null,
      "enabled": true,
      "group": null,
      "groupI18nCode": null,
      "subGroup": null,
      "subGroupI18nCode": null,
      "limitedLength": -1,
      "multiplier": 1,
      "elementUIHint": {
        "placeholder": null,
        "readonly": false,
        "reading": false,
        "required": true,
        "dataFormat": "String",
        "maskFormat": null,
        "textAlign": "Left",
        "editStyle": "RadioBox",
        "dictCodeMode": "DictCode",
        "dictCodeExpr": "CompanyTaxNature",
        "dictCodeLazy": false,
        "dictCodeTreeLeafOnly": false,
        "dictCodeTreeFull": false,
        "prefix": null,
        "suffix": null,
        "tips": null,
        "tipsI18nCode": null,
        "note": null,
        "noteI18nCode": null,
        "visible": true,
        "rank": 0,
        "mediaQuery": "xs",
        "htmlStyle": null,
        "colspan": 2,
        "eventExpr": null
      },
      "validatorList": [],
      "revision": 0,
      "createdBy": null,
      "createdTime": null,
      "updatedBy": null,
      "updatedTime": null
    },
    {
      "dataformId": "system-CorpInfo",
      "code": "taxNo",
      "primaryKey": false,
      "primaryKeyGenerator": null,
      "sortCode": "0050",
      "name": "税号",
      "nameI18nCode": null,
      "column": "TAX_NO",
      "table": null,
      "updateable": true,
      "sortable": false,
      "persist": true,
      "dataType": "String",
      "decimalDigits": -1,
      "defaultValue": null,
      "summaryExpression": null,
      "enabled": true,
      "group": null,
      "groupI18nCode": null,
      "subGroup": null,
      "subGroupI18nCode": null,
      "limitedLength": -1,
      "multiplier": 1,
      "elementUIHint": {
        "editStyle": "Text",
        "dataFormat": "String",
        "visible": true,
        "reading": false,
        "readonly": false,
        "required": true,
        "colspan": 2,
        "textAlign": "Left",
        "placeholder": null,
        "dictCodeMode": null,
        "dictCodeExpr": null,
        "dictCodeLazy": false,
        "dictCodeTreeLeafOnly": false,
        "dictCodeTreeFull": false,
        "prefix": null,
        "suffix": null,
        "tips": null,
        "tipsI18nCode": null,
        "note": null,
        "noteI18nCode": null,
        "rank": 0,
        "mediaQuery": "xs",
        "eventExpr": null,
        "htmlStyle": "{\"width\":\"250px\"}"
      },
      "validatorList": [],
      "revision": 0,
      "createdBy": null,
      "createdTime": null,
      "updatedBy": null,
      "updatedTime": null
    },
    {
      "dataformId": "system-CorpInfo",
      "code": "bankAccountNo",
      "primaryKey": false,
      "primaryKeyGenerator": null,
      "sortCode": "0060",
      "name": "银行账号",
      "nameI18nCode": null,
      "column": "BANK_ACCOUNT_NO",
      "table": null,
      "updateable": true,
      "sortable": false,
      "persist": true,
      "dataType": "String",
      "decimalDigits": -1,
      "defaultValue": null,
      "summaryExpression": null,
      "enabled": true,
      "group": null,
      "groupI18nCode": null,
      "subGroup": null,
      "subGroupI18nCode": null,
      "limitedLength": -1,
      "multiplier": 1,
      "elementUIHint": {
        "editStyle": "Text",
        "dataFormat": "String",
        "visible": true,
        "reading": false,
        "readonly": false,
        "required": true,
        "colspan": 1,
        "textAlign": "Left",
        "placeholder": null,
        "dictCodeMode": null,
        "dictCodeExpr": null,
        "dictCodeLazy": false,
        "dictCodeTreeLeafOnly": false,
        "dictCodeTreeFull": false,
        "prefix": null,
        "suffix": null,
        "tips": null,
        "tipsI18nCode": null,
        "note": null,
        "noteI18nCode": null,
        "rank": 0,
        "mediaQuery": "xs",
        "eventExpr": null,
        "htmlStyle": "{\"width\":\"250px\"}"
      },
      "validatorList": [],
      "revision": 0,
      "createdBy": null,
      "createdTime": null,
      "updatedBy": null,
      "updatedTime": null
    },
    {
      "dataformId": "system-CorpInfo",
      "code": "telephone",
      "primaryKey": false,
      "primaryKeyGenerator": null,
      "sortCode": "0070",
      "name": "电话",
      "nameI18nCode": null,
      "column": "TELEPHONE",
      "table": null,
      "updateable": true,
      "sortable": false,
      "persist": true,
      "dataType": "String",
      "decimalDigits": -1,
      "defaultValue": null,
      "summaryExpression": null,
      "enabled": true,
      "group": null,
      "groupI18nCode": null,
      "subGroup": null,
      "subGroupI18nCode": null,
      "limitedLength": -1,
      "multiplier": 1,
      "elementUIHint": {
        "editStyle": "Text",
        "dataFormat": "String",
        "visible": true,
        "reading": false,
        "readonly": false,
        "required": true,
        "colspan": 1,
        "textAlign": "Left",
        "placeholder": null,
        "dictCodeMode": null,
        "dictCodeExpr": null,
        "dictCodeLazy": false,
        "dictCodeTreeLeafOnly": false,
        "dictCodeTreeFull": false,
        "prefix": null,
        "suffix": null,
        "tips": null,
        "tipsI18nCode": null,
        "note": null,
        "noteI18nCode": null,
        "rank": 0,
        "mediaQuery": "xs",
        "eventExpr": null,
        "htmlStyle": "{\"width\":\"250px\"}"
      },
      "validatorList": [],
      "revision": 0,
      "createdBy": null,
      "createdTime": null,
      "updatedBy": null,
      "updatedTime": null
    },
    {
      "dataformId": "system-CorpInfo",
      "code": "raxRate",
      "primaryKey": false,
      "primaryKeyGenerator": null,
      "sortCode": "0080",
      "name": "税率",
      "nameI18nCode": null,
      "column": "RAX_RATE",
      "table": null,
      "updateable": true,
      "sortable": false,
      "persist": true,
      "dataType": "String",
      "decimalDigits": "0",
      "defaultValue": null,
      "summaryExpression": null,
      "enabled": true,
      "group": "",
      "groupI18nCode": null,
      "subGroup": null,
      "subGroupI18nCode": null,
      "limitedLength": -1,
      "multiplier": 1,
      "elementUIHint": {
        "editStyle": "Double",
        "dataFormat": "String",
        "visible": true,
        "reading": false,
        "readonly": false,
        "required": true,
        "colspan": 1,
        "textAlign": "Left",
        "placeholder": null,
        "dictCodeMode": null,
        "dictCodeExpr": null,
        "dictCodeLazy": false,
        "dictCodeTreeLeafOnly": false,
        "dictCodeTreeFull": false,
        "prefix": null,
        "suffix": "%",
        "tips": null,
        "tipsI18nCode": null,
        "note": null,
        "noteI18nCode": null,
        "rank": 0,
        "mediaQuery": "xs",
        "eventExpr": null,
        "htmlStyle": "{\"width\":\"250px\"}"
      },
      "validatorList": [],
      "revision": 0,
      "createdBy": null,
      "createdTime": null,
      "updatedBy": null,
      "updatedTime": null
    },
    {
      "dataformId": "system-CorpInfo",
      "code": "email",
      "primaryKey": false,
      "primaryKeyGenerator": null,
      "sortCode": "0090",
      "name": "电子邮件",
      "nameI18nCode": null,
      "column": "EMAIL",
      "table": null,
      "updateable": true,
      "sortable": false,
      "persist": true,
      "dataType": "String",
      "decimalDigits": -1,
      "defaultValue": null,
      "summaryExpression": null,
      "enabled": true,
      "group": null,
      "groupI18nCode": null,
      "subGroup": null,
      "subGroupI18nCode": null,
      "limitedLength": -1,
      "multiplier": 1,
      "elementUIHint": {
        "editStyle": "Text",
        "dataFormat": "String",
        "visible": true,
        "reading": false,
        "readonly": false,
        "required": false,
        "colspan": 1,
        "textAlign": "Left",
        "placeholder": null,
        "dictCodeMode": null,
        "dictCodeExpr": null,
        "dictCodeLazy": false,
        "dictCodeTreeLeafOnly": false,
        "dictCodeTreeFull": false,
        "prefix": null,
        "suffix": null,
        "tips": null,
        "tipsI18nCode": null,
        "note": null,
        "noteI18nCode": null,
        "rank": 0,
        "mediaQuery": "xs",
        "eventExpr": null,
        "htmlStyle": "{\"width\":\"250px\"}"
      },
      "validatorList": [],
      "revision": 0,
      "createdBy": null,
      "createdTime": null,
      "updatedBy": null,
      "updatedTime": null
    },
    {
      "dataformId": "system-CorpInfo",
      "code": "faxNo",
      "primaryKey": false,
      "primaryKeyGenerator": null,
      "sortCode": "0100",
      "name": "传真",
      "nameI18nCode": null,
      "column": "FAX_NO",
      "table": null,
      "updateable": true,
      "sortable": false,
      "persist": true,
      "dataType": "String",
      "decimalDigits": -1,
      "defaultValue": null,
      "summaryExpression": null,
      "enabled": true,
      "group": null,
      "groupI18nCode": null,
      "subGroup": null,
      "subGroupI18nCode": null,
      "limitedLength": -1,
      "multiplier": 1,
      "elementUIHint": {
        "editStyle": "Text",
        "dataFormat": "String",
        "visible": true,
        "reading": false,
        "readonly": false,
        "required": false,
        "colspan": 1,
        "textAlign": "Left",
        "placeholder": null,
        "dictCodeMode": null,
        "dictCodeExpr": null,
        "dictCodeLazy": false,
        "dictCodeTreeLeafOnly": false,
        "dictCodeTreeFull": false,
        "prefix": null,
        "suffix": null,
        "tips": null,
        "tipsI18nCode": null,
        "note": null,
        "noteI18nCode": null,
        "rank": 0,
        "mediaQuery": "xs",
        "eventExpr": null,
        "htmlStyle": "{\"width\":\"250px\"}"
      },
      "validatorList": [],
      "revision": 0,
      "createdBy": null,
      "createdTime": null,
      "updatedBy": null,
      "updatedTime": null
    },
    {
      "dataformId": "system-CorpInfo",
      "code": "address",
      "primaryKey": false,
      "primaryKeyGenerator": null,
      "sortCode": "0110",
      "name": "地址",
      "nameI18nCode": null,
      "column": "ADDRESS",
      "table": null,
      "updateable": true,
      "sortable": false,
      "persist": true,
      "dataType": "String",
      "decimalDigits": -1,
      "defaultValue": null,
      "summaryExpression": null,
      "enabled": true,
      "group": "",
      "groupI18nCode": null,
      "subGroup": null,
      "subGroupI18nCode": null,
      "limitedLength": -1,
      "multiplier": 1,
      "elementUIHint": {
        "editStyle": "TextArea",
        "dataFormat": "String",
        "visible": true,
        "reading": false,
        "readonly": false,
        "required": true,
        "colspan": 2,
        "textAlign": "Left",
        "placeholder": null,
        "dictCodeMode": null,
        "dictCodeExpr": null,
        "dictCodeLazy": false,
        "dictCodeTreeLeafOnly": false,
        "dictCodeTreeFull": false,
        "prefix": null,
        "suffix": null,
        "tips": null,
        "tipsI18nCode": null,
        "note": null,
        "noteI18nCode": null,
        "rank": 0,
        "mediaQuery": "xs",
        "eventExpr": null,
        "htmlStyle": "{\"width\":\"430px\",\"height\":\"200px\"}"
      },
      "validatorList": [],
      "revision": 0,
      "createdBy": null,
      "createdTime": null,
      "updatedBy": null,
      "updatedTime": null
    },
    {
      "dataformId": "system-CorpInfo",
      "code": "createdBy",
      "primaryKey": false,
      "primaryKeyGenerator": null,
      "sortCode": "0120",
      "name": "创建人",
      "nameI18nCode": null,
      "column": "CREATED_BY",
      "table": null,
      "updateable": true,
      "sortable": false,
      "persist": true,
      "dataType": "String",
      "decimalDigits": -1,
      "defaultValue": null,
      "summaryExpression": null,
      "enabled": true,
      "group": null,
      "groupI18nCode": null,
      "subGroup": null,
      "subGroupI18nCode": null,
      "limitedLength": -1,
      "multiplier": 1,
      "elementUIHint": {
        "placeholder": null,
        "readonly": false,
        "reading": false,
        "required": false,
        "dataFormat": "String",
        "maskFormat": null,
        "textAlign": "Left",
        "editStyle": "Text",
        "dictCodeMode": null,
        "dictCodeExpr": null,
        "dictCodeLazy": false,
        "dictCodeTreeLeafOnly": false,
        "dictCodeTreeFull": false,
        "prefix": null,
        "suffix": null,
        "tips": null,
        "tipsI18nCode": null,
        "note": null,
        "noteI18nCode": null,
        "visible": false,
        "rank": 0,
        "mediaQuery": "xs",
        "htmlStyle": null,
        "colspan": 1,
        "eventExpr": null
      },
      "validatorList": [],
      "revision": 0,
      "createdBy": null,
      "createdTime": null,
      "updatedBy": null,
      "updatedTime": null
    },
    {
      "dataformId": "system-CorpInfo",
      "code": "updatedBy",
      "primaryKey": false,
      "primaryKeyGenerator": null,
      "sortCode": "0130",
      "name": "更新人",
      "nameI18nCode": null,
      "column": "UPDATED_BY",
      "table": null,
      "updateable": true,
      "sortable": false,
      "persist": true,
      "dataType": "String",
      "decimalDigits": -1,
      "defaultValue": null,
      "summaryExpression": null,
      "enabled": true,
      "group": null,
      "groupI18nCode": null,
      "subGroup": null,
      "subGroupI18nCode": null,
      "limitedLength": -1,
      "multiplier": 1,
      "elementUIHint": {
        "placeholder": null,
        "readonly": false,
        "reading": false,
        "required": false,
        "dataFormat": "String",
        "maskFormat": null,
        "textAlign": "Left",
        "editStyle": "Text",
        "dictCodeMode": null,
        "dictCodeExpr": null,
        "dictCodeLazy": false,
        "dictCodeTreeLeafOnly": false,
        "dictCodeTreeFull": false,
        "prefix": null,
        "suffix": null,
        "tips": null,
        "tipsI18nCode": null,
        "note": null,
        "noteI18nCode": null,
        "visible": false,
        "rank": 0,
        "mediaQuery": "xs",
        "htmlStyle": null,
        "colspan": 1,
        "eventExpr": null
      },
      "validatorList": [],
      "revision": 0,
      "createdBy": null,
      "createdTime": null,
      "updatedBy": null,
      "updatedTime": null
    }
  ],
  "filters": [],
  "properties": {},
  "revision": 0,
  "createdBy": null,
  "createdTime": null,
  "updatedBy": null,
  "updatedTime": null
}