{
  "id": "configuration-FiscalBookInfo",
  "pack": "configuration",
  "code": "FiscalBookInfo",
  "name": "帐套配置详情页面",
  "description": "帐套配置详情页面",
  "sortCode": "0020",
  "classification": null,
  "tags": "帐套配置详情页面",
  "dataModelType": "DataMap",
  "dataModel": "FISC_BOOK",
  "query": {
    "select": "select",
    "selectItems": [],
    "from": "FISC_BOOK FB",
    "where": "BOOK_CODE=:bookCode",
    "groupBy": null,
    "having": null,
    "orderBy": "FB.CREATED_TIME DESC"
  },
  "handler": "com.vekai.appframe.conf.fiscalbook.handler.FiscalBookInfoHandler",
  "formUIHint": {
    "columnNumber": 2,
    "formStyle": "DetailInfo"
  },
  "elements": [
    {
      "dataformId": "configuration-FiscalBookSummary",
      "code": "bookCode",
      "primaryKey": true,
      "primaryKeyGenerator": null,
      "sortCode": "0000",
      "name": "账套代码",
      "nameI18nCode": null,
      "column": "BOOK_CODE",
      "table": "FB",
      "updateable": true,
      "sortable": false,
      "persist": true,
      "dataType": "String",
      "decimalDigits": -1,
      "defaultValue": null,
      "summaryExpression": null,
      "enabled": true,
      "group": "10:系统信息",
      "groupI18nCode": null,
      "subGroup": null,
      "subGroupI18nCode": null,
      "limitedLength": -1,
      "multiplier": 1,
      "elementUIHint": {
        "placeholder": null,
        "readonly": false,
        "reading": false,
        "required": true,
        "dataFormat": "String",
        "maskFormat": null,
        "textAlign": "Left",
        "editStyle": "Text",
        "dictCodeMode": null,
        "dictCodeExpr": null,
        "dictCodeLazy": false,
        "dictCodeTreeLeafOnly": false,
        "dictCodeTreeFull": false,
        "prefix": null,
        "suffix": null,
        "tips": null,
        "tipsI18nCode": null,
        "note": null,
        "noteI18nCode": null,
        "visible": true,
        "rank": 0,
        "mediaQuery": "xs",
        "htmlStyle": null,
        "colspan": 1,
        "eventExpr": null
      },
      "validatorList": [],
      "revision": 0,
      "createdBy": null,
      "createdTime": null,
      "updatedBy": null,
      "updatedTime": null
    },
    {
      "dataformId": "configuration-FiscalBookSummary",
      "code": "bookName",
      "primaryKey": false,
      "primaryKeyGenerator": null,
      "sortCode": "0010",
      "name": "账套名称",
      "nameI18nCode": null,
      "column": "BOOK_NAME",
      "table": "FB",
      "updateable": true,
      "sortable": false,
      "persist": true,
      "dataType": "String",
      "decimalDigits": -1,
      "defaultValue": null,
      "summaryExpression": null,
      "enabled": true,
      "group": "10:系统信息",
      "groupI18nCode": null,
      "subGroup": null,
      "subGroupI18nCode": null,
      "limitedLength": -1,
      "multiplier": 1,
      "elementUIHint": {
        "placeholder": null,
        "readonly": false,
        "reading": false,
        "required": true,
        "dataFormat": "String",
        "maskFormat": null,
        "textAlign": "Left",
        "editStyle": "Text",
        "dictCodeMode": null,
        "dictCodeExpr": null,
        "dictCodeLazy": false,
        "dictCodeTreeLeafOnly": false,
        "dictCodeTreeFull": false,
        "prefix": null,
        "suffix": null,
        "tips": null,
        "tipsI18nCode": null,
        "note": null,
        "noteI18nCode": null,
        "visible": true,
        "rank": 0,
        "mediaQuery": "xs",
        "htmlStyle": "{\"width\":\"577px\"}",
        "colspan": 2,
        "eventExpr": null
      },
      "validatorList": [],
      "revision": 0,
      "createdBy": null,
      "createdTime": null,
      "updatedBy": null,
      "updatedTime": null
    },
    {
      "dataformId": "configuration-FiscalBookSummary",
      "code": "mainCorpId",
      "primaryKey": false,
      "primaryKeyGenerator": null,
      "sortCode": "0012",
      "name": "主体公司Id",
      "nameI18nCode": null,
      "column": "MAIN_CORP_ID",
      "table": "FB",
      "updateable": true,
      "sortable": false,
      "persist": true,
      "dataType": "String",
      "decimalDigits": -1,
      "defaultValue": null,
      "summaryExpression": null,
      "enabled": true,
      "group": "10:系统信息",
      "groupI18nCode": null,
      "subGroup": null,
      "subGroupI18nCode": null,
      "limitedLength": -1,
      "multiplier": 1,
      "elementUIHint": {
        "placeholder": null,
        "readonly": false,
        "reading": false,
        "required": false,
        "dataFormat": "String",
        "maskFormat": null,
        "textAlign": "Left",
        "editStyle": "Text",
        "dictCodeMode": null,
        "dictCodeExpr": null,
        "dictCodeLazy": false,
        "dictCodeTreeLeafOnly": false,
        "dictCodeTreeFull": false,
        "prefix": null,
        "suffix": null,
        "tips": null,
        "tipsI18nCode": null,
        "note": null,
        "noteI18nCode": null,
        "visible": false,
        "rank": 0,
        "mediaQuery": "xs",
        "htmlStyle": null,
        "colspan": 1,
        "eventExpr": null
      },
      "validatorList": [],
      "revision": 0,
      "createdBy": null,
      "createdTime": null,
      "updatedBy": null,
      "updatedTime": null
    },
    {
      "dataformId": "configuration-FiscalBookSummary",
      "code": "mainCorpName",
      "primaryKey": false,
      "primaryKeyGenerator": null,
      "sortCode": "0015",
      "name": "主体公司名称",
      "nameI18nCode": null,
      "column": "MAIN_CORP_NAME",
      "table": "FB",
      "updateable": true,
      "sortable": false,
      "persist": true,
      "dataType": "String",
      "decimalDigits": -1,
      "defaultValue": null,
      "summaryExpression": null,
      "enabled": true,
      "group": "10:系统信息",
      "groupI18nCode": null,
      "subGroup": null,
      "subGroupI18nCode": null,
      "limitedLength": -1,
      "multiplier": 1,
      "elementUIHint": {
        "placeholder": null,
        "readonly": false,
        "reading": false,
        "required": true,
        "dataFormat": "String",
        "maskFormat": null,
        "textAlign": "Left",
        "editStyle": "Text",
        "dictCodeMode": null,
        "dictCodeExpr": null,
        "dictCodeLazy": false,
        "dictCodeTreeLeafOnly": false,
        "dictCodeTreeFull": false,
        "prefix": null,
        "suffix": null,
        "tips": null,
        "tipsI18nCode": null,
        "note": null,
        "noteI18nCode": null,
        "visible": true,
        "rank": 0,
        "mediaQuery": "xs",
        "htmlStyle": "{\"width\":\"577px\"}",
        "colspan": 2,
        "eventExpr": null
      },
      "validatorList": [],
      "revision": 0,
      "createdBy": null,
      "createdTime": null,
      "updatedBy": null,
      "updatedTime": null
    },
    {
      "dataformId": "configuration-FiscalBookSummary",
      "code": "unifiedCreditCode",
      "primaryKey": false,
      "primaryKeyGenerator": null,
      "sortCode": "0016",
      "name": "统一社会信用代码",
      "nameI18nCode": null,
      "column": "UNIFIED_CREDIT_CODE",
      "table": "FB",
      "updateable": true,
      "sortable": false,
      "persist": true,
      "dataType": "String",
      "decimalDigits": -1,
      "defaultValue": null,
      "summaryExpression": null,
      "enabled": true,
      "group": "10:系统信息",
      "groupI18nCode": null,
      "subGroup": null,
      "subGroupI18nCode": null,
      "limitedLength": -1,
      "multiplier": 1,
      "elementUIHint": {
        "placeholder": null,
        "readonly": false,
        "reading": false,
        "required": false,
        "dataFormat": "String",
        "maskFormat": null,
        "textAlign": "Left",
        "editStyle": "Text",
        "dictCodeMode": null,
        "dictCodeExpr": null,
        "dictCodeLazy": false,
        "dictCodeTreeLeafOnly": false,
        "dictCodeTreeFull": false,
        "prefix": null,
        "suffix": null,
        "tips": null,
        "tipsI18nCode": null,
        "note": null,
        "noteI18nCode": null,
        "visible": true,
        "rank": 0,
        "mediaQuery": "xs",
        "htmlStyle": null,
        "colspan": 1,
        "eventExpr": null
      },
      "validatorList": [],
      "revision": 0,
      "createdBy": null,
      "createdTime": null,
      "updatedBy": null,
      "updatedTime": null
    },
    {
      "dataformId": "configuration-FiscalBookSummary",
      "code": "taxNature",
      "primaryKey": false,
      "primaryKeyGenerator": null,
      "sortCode": "0018",
      "name": "主体公司纳税性质",
      "nameI18nCode": null,
      "column": "TAX_NATURE",
      "table": "FB",
      "updateable": true,
      "sortable": false,
      "persist": true,
      "dataType": "String",
      "decimalDigits": -1,
      "defaultValue": null,
      "summaryExpression": null,
      "enabled": true,
      "group": "10:系统信息",
      "groupI18nCode": null,
      "subGroup": null,
      "subGroupI18nCode": null,
      "limitedLength": -1,
      "multiplier": 1,
      "elementUIHint": {
        "placeholder": null,
        "readonly": false,
        "reading": false,
        "required": true,
        "dataFormat": "String",
        "maskFormat": null,
        "textAlign": "Left",
        "editStyle": "RadioBox",
        "dictCodeMode": "DictCode",
        "dictCodeExpr": "CompanyTaxNature",
        "dictCodeLazy": false,
        "dictCodeTreeLeafOnly": false,
        "dictCodeTreeFull": false,
        "prefix": null,
        "suffix": null,
        "tips": null,
        "tipsI18nCode": null,
        "note": null,
        "noteI18nCode": null,
        "visible": true,
        "rank": 0,
        "mediaQuery": "xs",
        "htmlStyle": null,
        "colspan": 2,
        "eventExpr": null
      },
      "validatorList": [],
      "revision": 0,
      "createdBy": null,
      "createdTime": null,
      "updatedBy": null,
      "updatedTime": null
    },
    {
      "dataformId": "configuration-FiscalBookSummary",
      "code": "telephone",
      "primaryKey": false,
      "primaryKeyGenerator": null,
      "sortCode": "0019",
      "name": "电话",
      "nameI18nCode": null,
      "column": "TELEPHONE",
      "table": "FB",
      "updateable": true,
      "sortable": false,
      "persist": true,
      "dataType": "String",
      "decimalDigits": -1,
      "defaultValue": null,
      "summaryExpression": null,
      "enabled": true,
      "group": "10:系统信息",
      "groupI18nCode": null,
      "subGroup": null,
      "subGroupI18nCode": null,
      "limitedLength": -1,
      "multiplier": 1,
      "elementUIHint": {
        "placeholder": null,
        "readonly": false,
        "reading": false,
        "required": false,
        "dataFormat": "String",
        "maskFormat": null,
        "textAlign": "Left",
        "editStyle": "Text",
        "dictCodeMode": null,
        "dictCodeExpr": null,
        "dictCodeLazy": false,
        "dictCodeTreeLeafOnly": false,
        "dictCodeTreeFull": false,
        "prefix": null,
        "suffix": null,
        "tips": null,
        "tipsI18nCode": null,
        "note": null,
        "noteI18nCode": null,
        "visible": true,
        "rank": 0,
        "mediaQuery": "xs",
        "htmlStyle": null,
        "colspan": 1,
        "eventExpr": null
      },
      "validatorList": [],
      "revision": 0,
      "createdBy": null,
      "createdTime": null,
      "updatedBy": null,
      "updatedTime": null
    },
    {
      "dataformId": "configuration-FiscalBookSummary",
      "code": "email",
      "primaryKey": false,
      "primaryKeyGenerator": null,
      "sortCode": "0022",
      "name": "电子邮件",
      "nameI18nCode": null,
      "column": "EMAIL",
      "table": "FB",
      "updateable": true,
      "sortable": false,
      "persist": true,
      "dataType": "String",
      "decimalDigits": -1,
      "defaultValue": null,
      "summaryExpression": null,
      "enabled": true,
      "group": "10:系统信息",
      "groupI18nCode": null,
      "subGroup": null,
      "subGroupI18nCode": null,
      "limitedLength": -1,
      "multiplier": 1,
      "elementUIHint": {
        "placeholder": null,
        "readonly": false,
        "reading": false,
        "required": false,
        "dataFormat": "String",
        "maskFormat": null,
        "textAlign": "Left",
        "editStyle": "Text",
        "dictCodeMode": null,
        "dictCodeExpr": null,
        "dictCodeLazy": false,
        "dictCodeTreeLeafOnly": false,
        "dictCodeTreeFull": false,
        "prefix": null,
        "suffix": null,
        "tips": null,
        "tipsI18nCode": null,
        "note": null,
        "noteI18nCode": null,
        "visible": true,
        "rank": 0,
        "mediaQuery": "xs",
        "htmlStyle": "{\"width\":\"200px\"}",
        "colspan": 1,
        "eventExpr": null
      },
      "validatorList": [],
      "revision": 0,
      "createdBy": null,
      "createdTime": null,
      "updatedBy": null,
      "updatedTime": null
    },
    {
      "dataformId": "configuration-FiscalBookSummary",
      "code": "faxNo",
      "primaryKey": false,
      "primaryKeyGenerator": null,
      "sortCode": "0025",
      "name": "传真",
      "nameI18nCode": null,
      "column": "FAX_NO",
      "table": "FB",
      "updateable": true,
      "sortable": false,
      "persist": true,
      "dataType": "String",
      "decimalDigits": -1,
      "defaultValue": null,
      "summaryExpression": null,
      "enabled": true,
      "group": "10:系统信息",
      "groupI18nCode": null,
      "subGroup": null,
      "subGroupI18nCode": null,
      "limitedLength": -1,
      "multiplier": 1,
      "elementUIHint": {
        "placeholder": null,
        "readonly": false,
        "reading": false,
        "required": false,
        "dataFormat": "String",
        "maskFormat": null,
        "textAlign": "Left",
        "editStyle": "Text",
        "dictCodeMode": null,
        "dictCodeExpr": null,
        "dictCodeLazy": false,
        "dictCodeTreeLeafOnly": false,
        "dictCodeTreeFull": false,
        "prefix": null,
        "suffix": null,
        "tips": null,
        "tipsI18nCode": null,
        "note": null,
        "noteI18nCode": null,
        "visible": true,
        "rank": 0,
        "mediaQuery": "xs",
        "htmlStyle": null,
        "colspan": 1,
        "eventExpr": null
      },
      "validatorList": [],
      "revision": 0,
      "createdBy": null,
      "createdTime": null,
      "updatedBy": null,
      "updatedTime": null
    },
    {
      "dataformId": "configuration-FiscalBookSummary",
      "code": "bankAccountNo",
      "primaryKey": false,
      "primaryKeyGenerator": null,
      "sortCode": "0026",
      "name": "银行账号",
      "nameI18nCode": null,
      "column": "BANK_ACCOUNT_NO",
      "table": "FB",
      "updateable": true,
      "sortable": false,
      "persist": true,
      "dataType": "String",
      "decimalDigits": -1,
      "defaultValue": null,
      "summaryExpression": null,
      "enabled": true,
      "group": "10:系统信息",
      "groupI18nCode": null,
      "subGroup": null,
      "subGroupI18nCode": null,
      "limitedLength": -1,
      "multiplier": 1,
      "elementUIHint": {
        "placeholder": null,
        "readonly": false,
        "reading": false,
        "required": false,
        "dataFormat": "String",
        "maskFormat": null,
        "textAlign": "Left",
        "editStyle": "Text",
        "dictCodeMode": null,
        "dictCodeExpr": null,
        "dictCodeLazy": false,
        "dictCodeTreeLeafOnly": false,
        "dictCodeTreeFull": false,
        "prefix": null,
        "suffix": null,
        "tips": null,
        "tipsI18nCode": null,
        "note": null,
        "noteI18nCode": null,
        "visible": true,
        "rank": 0,
        "mediaQuery": "xs",
        "htmlStyle": "{\"width\":\"230px\"}",
        "colspan": 1,
        "eventExpr": null
      },
      "validatorList": [],
      "revision": 0,
      "createdBy": null,
      "createdTime": null,
      "updatedBy": null,
      "updatedTime": null
    },
    {
      "dataformId": "configuration-FiscalBookSummary",
      "code": "taxNo",
      "primaryKey": false,
      "primaryKeyGenerator": null,
      "sortCode": "0032",
      "name": "税号",
      "nameI18nCode": null,
      "column": "TAX_NO",
      "table": "FB",
      "updateable": true,
      "sortable": false,
      "persist": true,
      "dataType": "String",
      "decimalDigits": -1,
      "defaultValue": null,
      "summaryExpression": null,
      "enabled": true,
      "group": "10:系统信息",
      "groupI18nCode": null,
      "subGroup": null,
      "subGroupI18nCode": null,
      "limitedLength": -1,
      "multiplier": 1,
      "elementUIHint": {
        "placeholder": null,
        "readonly": false,
        "reading": false,
        "required": true,
        "dataFormat": "String",
        "maskFormat": null,
        "textAlign": "Left",
        "editStyle": "Text",
        "dictCodeMode": null,
        "dictCodeExpr": null,
        "dictCodeLazy": false,
        "dictCodeTreeLeafOnly": false,
        "dictCodeTreeFull": false,
        "prefix": null,
        "suffix": null,
        "tips": null,
        "tipsI18nCode": null,
        "note": null,
        "noteI18nCode": null,
        "visible": true,
        "rank": 0,
        "mediaQuery": "xs",
        "htmlStyle": null,
        "colspan": 1,
        "eventExpr": null
      },
      "validatorList": [],
      "revision": 0,
      "createdBy": null,
      "createdTime": null,
      "updatedBy": null,
      "updatedTime": null
    },
    {
      "dataformId": "configuration-FiscalBookSummary",
      "code": "raxRate",
      "primaryKey": false,
      "primaryKeyGenerator": null,
      "sortCode": "0033",
      "name": "税率",
      "nameI18nCode": null,
      "column": "RAX_RATE",
      "table": "FB",
      "updateable": true,
      "sortable": false,
      "persist": true,
      "dataType": "Double",
      "decimalDigits": 2,
      "defaultValue": null,
      "summaryExpression": null,
      "enabled": true,
      "group": "10:系统信息",
      "groupI18nCode": null,
      "subGroup": null,
      "subGroupI18nCode": null,
      "limitedLength": -1,
      "multiplier": 0.01,
      "elementUIHint": {
        "placeholder": null,
        "readonly": false,
        "reading": false,
        "required": true,
        "dataFormat": "Double",
        "maskFormat": null,
        "textAlign": "Left",
        "editStyle": "Double",
        "dictCodeMode": null,
        "dictCodeExpr": null,
        "dictCodeLazy": false,
        "dictCodeTreeLeafOnly": false,
        "dictCodeTreeFull": false,
        "prefix": null,
        "suffix": "%",
        "tips": null,
        "tipsI18nCode": null,
        "note": null,
        "noteI18nCode": null,
        "visible": true,
        "rank": 0,
        "mediaQuery": "xs",
        "htmlStyle": null,
        "colspan": 1,
        "eventExpr": null
      },
      "validatorList": [],
      "revision": 0,
      "createdBy": null,
      "createdTime": null,
      "updatedBy": null,
      "updatedTime": null
    },
    {
      "dataformId": "configuration-FiscalBookSummary",
      "code": "address",
      "primaryKey": false,
      "primaryKeyGenerator": null,
      "sortCode": "0034",
      "name": "地址",
      "nameI18nCode": null,
      "column": "ADDRESS",
      "table": "FB",
      "updateable": true,
      "sortable": false,
      "persist": true,
      "dataType": "String",
      "decimalDigits": -1,
      "defaultValue": null,
      "summaryExpression": null,
      "enabled": true,
      "group": "10:系统信息",
      "groupI18nCode": null,
      "subGroup": null,
      "subGroupI18nCode": null,
      "limitedLength": -1,
      "multiplier": 1,
      "elementUIHint": {
        "placeholder": null,
        "readonly": false,
        "reading": false,
        "required": false,
        "dataFormat": "String",
        "maskFormat": null,
        "textAlign": "Left",
        "editStyle": "Text",
        "dictCodeMode": null,
        "dictCodeExpr": null,
        "dictCodeLazy": false,
        "dictCodeTreeLeafOnly": false,
        "dictCodeTreeFull": false,
        "prefix": null,
        "suffix": null,
        "tips": null,
        "tipsI18nCode": null,
        "note": null,
        "noteI18nCode": null,
        "visible": true,
        "rank": 0,
        "mediaQuery": "xs",
        "htmlStyle": "{\"width\":\"577px\"}",
        "colspan": 2,
        "eventExpr": null
      },
      "validatorList": [],
      "revision": 0,
      "createdBy": null,
      "createdTime": null,
      "updatedBy": null,
      "updatedTime": null
    },
    {
      "dataformId": "configuration-FiscalBookSummary",
      "code": "startYear",
      "primaryKey": false,
      "primaryKeyGenerator": null,
      "sortCode": "0035",
      "name": "启用会计年度",
      "nameI18nCode": null,
      "column": "START_YEAR",
      "table": "FB",
      "updateable": true,
      "sortable": false,
      "persist": true,
      "dataType": "Integer",
      "decimalDigits": 0,
      "defaultValue": null,
      "summaryExpression": null,
      "enabled": true,
      "group": "20:参数设置",
      "groupI18nCode": null,
      "subGroup": null,
      "subGroupI18nCode": null,
      "limitedLength": 4,
      "multiplier": 1,
      "elementUIHint": {
        "placeholder": null,
        "readonly": false,
        "reading": false,
        "required": true,
        "dataFormat": "Double",
        "maskFormat": null,
        "textAlign": "Left",
        "editStyle": "Integer",
        "dictCodeMode": null,
        "dictCodeExpr": null,
        "dictCodeLazy": false,
        "dictCodeTreeLeafOnly": false,
        "dictCodeTreeFull": false,
        "prefix": null,
        "suffix": null,
        "tips": null,
        "tipsI18nCode": null,
        "note": null,
        "noteI18nCode": null,
        "visible": true,
        "rank": 0,
        "mediaQuery": "xs",
        "htmlStyle": null,
        "colspan": 1,
        "eventExpr": null
      },
      "validatorList": [],
      "revision": 0,
      "createdBy": null,
      "createdTime": null,
      "updatedBy": null,
      "updatedTime": null
    },
    {
      "dataformId": "configuration-FiscalBookSummary",
      "code": "startTerm",
      "primaryKey": false,
      "primaryKeyGenerator": null,
      "sortCode": "0040",
      "name": "启用会计期间",
      "nameI18nCode": null,
      "column": "START_TERM",
      "table": "FB",
      "updateable": true,
      "sortable": false,
      "persist": true,
      "dataType": "Integer",
      "decimalDigits": 0,
      "defaultValue": null,
      "summaryExpression": null,
      "enabled": true,
      "group": "20:参数设置",
      "groupI18nCode": null,
      "subGroup": null,
      "subGroupI18nCode": null,
      "limitedLength": 2,
      "multiplier": 1,
      "elementUIHint": {
        "placeholder": null,
        "readonly": false,
        "reading": false,
        "required": true,
        "dataFormat": "Double",
        "maskFormat": null,
        "textAlign": "Left",
        "editStyle": "Integer",
        "dictCodeMode": null,
        "dictCodeExpr": null,
        "dictCodeLazy": false,
        "dictCodeTreeLeafOnly": false,
        "dictCodeTreeFull": false,
        "prefix": null,
        "suffix": null,
        "tips": null,
        "tipsI18nCode": null,
        "note": null,
        "noteI18nCode": null,
        "visible": true,
        "rank": 0,
        "mediaQuery": "xs",
        "htmlStyle": null,
        "colspan": 1,
        "eventExpr": null
      },
      "validatorList": [],
      "revision": 0,
      "createdBy": null,
      "createdTime": null,
      "updatedBy": null,
      "updatedTime": null
    },
    {
      "dataformId": "configuration-FiscalBookSummary",
      "code": "currentYear",
      "primaryKey": false,
      "primaryKeyGenerator": null,
      "sortCode": "0050",
      "name": "当前会计年度",
      "nameI18nCode": null,
      "column": "CURRENT_YEAR",
      "table": "FB",
      "updateable": true,
      "sortable": false,
      "persist": true,
      "dataType": "Integer",
      "decimalDigits": 0,
      "defaultValue": null,
      "summaryExpression": null,
      "enabled": true,
      "group": "20:参数设置",
      "groupI18nCode": null,
      "subGroup": null,
      "subGroupI18nCode": null,
      "limitedLength": 4,
      "multiplier": 1,
      "elementUIHint": {
        "placeholder": null,
        "readonly": false,
        "reading": false,
        "required": false,
        "dataFormat": "Double",
        "maskFormat": null,
        "textAlign": "Left",
        "editStyle": "Integer",
        "dictCodeMode": null,
        "dictCodeExpr": null,
        "dictCodeLazy": false,
        "dictCodeTreeLeafOnly": false,
        "dictCodeTreeFull": false,
        "prefix": null,
        "suffix": null,
        "tips": null,
        "tipsI18nCode": null,
        "note": null,
        "noteI18nCode": null,
        "visible": false,
        "rank": 0,
        "mediaQuery": "xs",
        "htmlStyle": null,
        "colspan": 1,
        "eventExpr": null
      },
      "validatorList": [],
      "revision": 0,
      "createdBy": null,
      "createdTime": null,
      "updatedBy": null,
      "updatedTime": null
    },
    {
      "dataformId": "configuration-FiscalBookSummary",
      "code": "currentTerm",
      "primaryKey": false,
      "primaryKeyGenerator": null,
      "sortCode": "0060",
      "name": "当前会计期间",
      "nameI18nCode": null,
      "column": "CURRENT_TERM",
      "table": "FB",
      "updateable": true,
      "sortable": false,
      "persist": true,
      "dataType": "Integer",
      "decimalDigits": 0,
      "defaultValue": null,
      "summaryExpression": null,
      "enabled": true,
      "group": "20:参数设置",
      "groupI18nCode": null,
      "subGroup": null,
      "subGroupI18nCode": null,
      "limitedLength": 2,
      "multiplier": 1,
      "elementUIHint": {
        "placeholder": null,
        "readonly": true,
        "reading": false,
        "required": false,
        "dataFormat": "Double",
        "maskFormat": null,
        "textAlign": "Left",
        "editStyle": "Integer",
        "dictCodeMode": null,
        "dictCodeExpr": null,
        "dictCodeLazy": false,
        "dictCodeTreeLeafOnly": false,
        "dictCodeTreeFull": false,
        "prefix": null,
        "suffix": null,
        "tips": null,
        "tipsI18nCode": null,
        "note": null,
        "noteI18nCode": null,
        "visible": true,
        "rank": 0,
        "mediaQuery": "xs",
        "htmlStyle": null,
        "colspan": 1,
        "eventExpr": null
      },
      "validatorList": [],
      "revision": 0,
      "createdBy": null,
      "createdTime": null,
      "updatedBy": null,
      "updatedTime": null
    },
    {
      "dataformId": "configuration-FiscalBookSummary",
      "code": "gaapDef",
      "primaryKey": false,
      "primaryKeyGenerator": null,
      "sortCode": "0070",
      "name": "会计准则制度",
      "nameI18nCode": null,
      "column": "GAAP_DEF",
      "table": "FB",
      "updateable": true,
      "sortable": false,
      "persist": true,
      "dataType": "String",
      "decimalDigits": -1,
      "defaultValue": null,
      "summaryExpression": null,
      "enabled": true,
      "group": "30:基本信息",
      "groupI18nCode": null,
      "subGroup": null,
      "subGroupI18nCode": null,
      "limitedLength": -1,
      "multiplier": 1,
      "elementUIHint": {
        "placeholder": null,
        "readonly": false,
        "reading": false,
        "required": true,
        "dataFormat": "String",
        "maskFormat": null,
        "textAlign": "Left",
        "editStyle": "Text",
        "dictCodeMode": null,
        "dictCodeExpr": null,
        "dictCodeLazy": false,
        "dictCodeTreeLeafOnly": false,
        "dictCodeTreeFull": false,
        "prefix": null,
        "suffix": null,
        "tips": null,
        "tipsI18nCode": null,
        "note": null,
        "noteI18nCode": null,
        "visible": false,
        "rank": 0,
        "mediaQuery": "xs",
        "htmlStyle": null,
        "colspan": 2,
        "eventExpr": null
      },
      "validatorList": [],
      "revision": 0,
      "createdBy": null,
      "createdTime": null,
      "updatedBy": null,
      "updatedTime": null
    },
    {
      "dataformId": "configuration-FiscalBookSummary",
      "code": "gaapName",
      "primaryKey": false,
      "primaryKeyGenerator": null,
      "sortCode": "0080",
      "name": "会计准则制度名称",
      "nameI18nCode": null,
      "column": "GAAP_NAME",
      "table": "FB",
      "updateable": true,
      "sortable": false,
      "persist": true,
      "dataType": "String",
      "decimalDigits": -1,
      "defaultValue": null,
      "summaryExpression": null,
      "enabled": true,
      "group": "30:基本信息",
      "groupI18nCode": null,
      "subGroup": null,
      "subGroupI18nCode": null,
      "limitedLength": -1,
      "multiplier": 1,
      "elementUIHint": {
        "placeholder": null,
        "readonly": true,
        "reading": false,
        "required": true,
        "dataFormat": "String",
        "maskFormat": null,
        "textAlign": "Left",
        "editStyle": "Text",
        "dictCodeMode": null,
        "dictCodeExpr": null,
        "dictCodeLazy": false,
        "dictCodeTreeLeafOnly": false,
        "dictCodeTreeFull": false,
        "prefix": null,
        "suffix": null,
        "tips": null,
        "tipsI18nCode": null,
        "note": null,
        "noteI18nCode": null,
        "visible": true,
        "rank": 0,
        "mediaQuery": "xs",
        "htmlStyle": null,
        "colspan": 2,
        "eventExpr": null
      },
      "validatorList": [],
      "revision": 0,
      "createdBy": null,
      "createdTime": null,
      "updatedBy": null,
      "updatedTime": null
    },
    {
      "dataformId": "configuration-FiscalBookSummary",
      "code": "voucherWord",
      "primaryKey": false,
      "primaryKeyGenerator": null,
      "sortCode": "0090",
      "name": "凭证字",
      "nameI18nCode": null,
      "column": "VOUCHER_WORD",
      "table": "FB",
      "updateable": true,
      "sortable": false,
      "persist": true,
      "dataType": "String",
      "decimalDigits": -1,
      "defaultValue": null,
      "summaryExpression": null,
      "enabled": true,
      "group": "30:基本信息",
      "groupI18nCode": null,
      "subGroup": null,
      "subGroupI18nCode": null,
      "limitedLength": -1,
      "multiplier": 1,
      "elementUIHint": {
        "placeholder": null,
        "readonly": false,
        "reading": false,
        "required": true,
        "dataFormat": "String",
        "maskFormat": null,
        "textAlign": "Left",
        "editStyle": "RadioBox",
        "dictCodeMode": "DictCode",
        "dictCodeExpr": "VoucherWord",
        "dictCodeLazy": false,
        "dictCodeTreeLeafOnly": false,
        "dictCodeTreeFull": false,
        "prefix": null,
        "suffix": null,
        "tips": null,
        "tipsI18nCode": null,
        "note": null,
        "noteI18nCode": null,
        "visible": true,
        "rank": 0,
        "mediaQuery": "xs",
        "htmlStyle": null,
        "colspan": 2,
        "eventExpr": null
      },
      "validatorList": [],
      "revision": 0,
      "createdBy": null,
      "createdTime": null,
      "updatedBy": null,
      "updatedTime": null
    },
    {
      "dataformId": "configuration-FiscalBookSummary",
      "code": "currency",
      "primaryKey": false,
      "primaryKeyGenerator": null,
      "sortCode": "0140",
      "name": "本位币",
      "nameI18nCode": null,
      "column": "CURRENCY",
      "table": "FB",
      "updateable": true,
      "sortable": false,
      "persist": true,
      "dataType": "String",
      "decimalDigits": -1,
      "defaultValue": null,
      "summaryExpression": null,
      "enabled": true,
      "group": "20:参数设置",
      "groupI18nCode": null,
      "subGroup": null,
      "subGroupI18nCode": null,
      "limitedLength": -1,
      "multiplier": 1,
      "elementUIHint": {
        "placeholder": null,
        "readonly": false,
        "reading": false,
        "required": true,
        "dataFormat": "String",
        "maskFormat": null,
        "textAlign": "Left",
        "editStyle": "Select",
        "dictCodeMode": "DictCode",
        "dictCodeExpr": "Currency",
        "dictCodeLazy": false,
        "dictCodeTreeLeafOnly": false,
        "dictCodeTreeFull": false,
        "prefix": null,
        "suffix": null,
        "tips": null,
        "tipsI18nCode": null,
        "note": null,
        "noteI18nCode": null,
        "visible": true,
        "rank": 0,
        "mediaQuery": "xs",
        "htmlStyle": "{\"width\":\"200px\"}",
        "colspan": 1,
        "eventExpr": null
      },
      "validatorList": [],
      "revision": 0,
      "createdBy": null,
      "createdTime": null,
      "updatedBy": null,
      "updatedTime": null
    },
    {
      "dataformId": "configuration-FiscalBookSummary",
      "code": "scalePrecision",
      "primaryKey": false,
      "primaryKeyGenerator": null,
      "sortCode": "0150",
      "name": "小数位数",
      "nameI18nCode": null,
      "column": "SCALE_PRECISION",
      "table": "FB",
      "updateable": true,
      "sortable": false,
      "persist": true,
      "dataType": "Integer",
      "decimalDigits": 0,
      "defaultValue": null,
      "summaryExpression": null,
      "enabled": true,
      "group": "20:参数设置",
      "groupI18nCode": null,
      "subGroup": null,
      "subGroupI18nCode": null,
      "limitedLength": -1,
      "multiplier": 1,
      "elementUIHint": {
        "placeholder": null,
        "readonly": false,
        "reading": false,
        "required": true,
        "dataFormat": "Double",
        "maskFormat": null,
        "textAlign": "Left",
        "editStyle": "Integer",
        "dictCodeMode": null,
        "dictCodeExpr": null,
        "dictCodeLazy": false,
        "dictCodeTreeLeafOnly": false,
        "dictCodeTreeFull": false,
        "prefix": null,
        "suffix": null,
        "tips": null,
        "tipsI18nCode": null,
        "note": null,
        "noteI18nCode": null,
        "visible": true,
        "rank": 0,
        "mediaQuery": "xs",
        "htmlStyle": null,
        "colspan": 1,
        "eventExpr": null
      },
      "validatorList": [],
      "revision": 0,
      "createdBy": null,
      "createdTime": null,
      "updatedBy": null,
      "updatedTime": null
    },
    {
      "dataformId": "configuration-FiscalBookSummary",
      "code": "bookIntro",
      "primaryKey": false,
      "primaryKeyGenerator": null,
      "sortCode": "0155",
      "name": "账套说明",
      "nameI18nCode": null,
      "column": "BOOK_INTRO",
      "table": "FB",
      "updateable": true,
      "sortable": false,
      "persist": true,
      "dataType": "String",
      "decimalDigits": -1,
      "defaultValue": null,
      "summaryExpression": null,
      "enabled": true,
      "group": "20:参数设置",
      "groupI18nCode": null,
      "subGroup": null,
      "subGroupI18nCode": null,
      "limitedLength": -1,
      "multiplier": 1,
      "elementUIHint": {
        "placeholder": null,
        "readonly": false,
        "reading": false,
        "required": false,
        "dataFormat": "String",
        "maskFormat": null,
        "textAlign": "Left",
        "editStyle": "TextArea",
        "dictCodeMode": null,
        "dictCodeExpr": null,
        "dictCodeLazy": false,
        "dictCodeTreeLeafOnly": false,
        "dictCodeTreeFull": false,
        "prefix": null,
        "suffix": null,
        "tips": null,
        "tipsI18nCode": null,
        "note": null,
        "noteI18nCode": null,
        "visible": true,
        "rank": 0,
        "mediaQuery": "xs",
        "htmlStyle": "{\"width\":\"577px\"}",
        "colspan": 2,
        "eventExpr": null
      },
      "validatorList": [],
      "revision": 0,
      "createdBy": null,
      "createdTime": null,
      "updatedBy": null,
      "updatedTime": null
    }
  ],
  "filters": [],
  "properties": {},
  "revision": 0,
  "createdBy": null,
  "createdTime": null,
  "updatedBy": null,
  "updatedTime": null
}